metabomics/__init__.py
metabomics/main_create_imputer_models.py
metabomics/main_filling.py
metabomics/main_flux_type_performance_test.py
metabomics/main_metabolights_pipeline.py
metabomics/main_tune_imputer_models.py
metabomics/main_workbench_pipeline.py
metabomics/mean_react_diff_scores.py
metabomics/metabolights_data_pipeline.py
metabomics/metabolights_downloader.py
metabomics/setup.py
metabomics/tests.py
metabomics/workbench_data_pipeline.py
metabomics/analysis/__init__.py
metabomics/analysis/analysis.py
metabomics/analysis/analysis_equal_val.py
metabomics/analysis/analysis_firstVersion.py
metabomics/analysis/analysis_max_trigger.py
metabomics/analysis/analysis_total_trig.py
metabomics/analysis/analysis_update_coeff.py
metabomics/analysis/analysis_v1.py
metabomics/analysis/analysis_v2.py
metabomics/analysis/drugAnalysis.py
metabomics/analysis/tests.py
metabomics/analysis/Data/Uniprot_Entrez_Converter.json
metabomics/analysis/Data/converter301.json
metabomics/analysis/Data/drug_target_UniprotID_all.json
metabomics/analysis/Data/uniprot_hgnc_converter.json
metabomics/cobra/__init__.py
metabomics/cobra/exceptions.py
metabomics/cobra/core/__init__.py
metabomics/cobra/core/configuration.py
metabomics/cobra/core/dictlist.py
metabomics/cobra/core/formula.py
metabomics/cobra/core/gene.py
metabomics/cobra/core/group.py
metabomics/cobra/core/metabolite.py
metabomics/cobra/core/model.py
metabomics/cobra/core/object.py
metabomics/cobra/core/reaction.py
metabomics/cobra/core/singleton.py
metabomics/cobra/core/solution.py
metabomics/cobra/core/species.py
metabomics/cobra/flux_analysis/__init__.py
metabomics/cobra/flux_analysis/deletion.py
metabomics/cobra/flux_analysis/fastcc.py
metabomics/cobra/flux_analysis/gapfilling.py
metabomics/cobra/flux_analysis/geometric.py
metabomics/cobra/flux_analysis/helpers.py
metabomics/cobra/flux_analysis/loopless.py
metabomics/cobra/flux_analysis/moma.py
metabomics/cobra/flux_analysis/parsimonious.py
metabomics-0.1.38.dist-info/LICENSE
metabomics-0.1.38.dist-info/METADATA
metabomics-0.1.38.dist-info/WHEEL
metabomics-0.1.38.dist-info/top_level.txt
metabomics-0.1.38.dist-info/RECORD
