Metadata-Version: 2.1
Name: metabOmics
Version: 0.1.38
Summary: metabOmics — tools for metabolomics and metabolic network analysis
Home-page: https://github.com/itu-bioinformatics-database-lab/metabOmics
Author: itu-bioinformatics-database-lab
Author-email: 
License: GNU GENERAL PUBLIC LICENSE
Project-URL: Homepage, https://github.com/itu-bioinformatics-database-lab/metabOmics
Project-URL: Source, https://github.com/itu-bioinformatics-database-lab/metabOmics
Keywords: metabolomics,metabolic networks,bioinformatics
Classifier: Programming Language :: Python :: 3
Classifier: License :: OSI Approved :: MIT License
Classifier: Operating System :: OS Independent
Requires-Python: >=3.9
License-File: LICENSE
